ExtremeLy/__init__.py
ExtremeLy/extremely.py
ExtremeLy-2.3.0.dist-info/METADATA
ExtremeLy-2.3.0.dist-info/WHEEL
ExtremeLy-2.3.0.dist-info/top_level.txt
ExtremeLy-2.3.0.dist-info/RECORD
