Metadata-Version: 2.1
Name: ExtremeLy
Version: 2.3.0
Summary: Extrem value Analysis in Python
Home-page: https://github.com/SURYA-LAMICHANEY/ExtremeLy
Author: Surya Lamichaney
Author-email: suryalamichaney38741@gmail.com
License: MIT
Project-URL: GitHub, https://github.com/SURYA-LAMICHANEY/ExtremeLy
Project-URL: PyPI, https://pypi.org/project/ExtremeLy/
Project-URL: Documentation, https://surya-lamichaney.github.io/ExtremeLy/
Keywords: Extreme Value Analysis,Block Maxima,Peak-Over-Threshold,Generalized Extreme Value Distribution (GEV),Generalized Pareto Distribution (GPD)
Platform: linux
Platform: windows
Platform: mac
Classifier: Development Status :: 3 - Alpha
Classifier: Intended Audience :: Science/Research
Classifier: Intended Audience :: Developers
Classifier: License :: OSI Approved :: MIT License
Classifier: Operating System :: OS Independent
Classifier: Programming Language :: Python :: 3.7
Classifier: Programming Language :: Python :: 3.8
Requires-Python: >=3.8
Requires-Dist: evt
